Wrapper_Weather_Module_V2/__init__.py
Wrapper_Weather_Module_V2/functions.py
Wrapper_Weather_Module_V2/main.py
Wrapper_Weather_Module_V2-0.0.1.dist-info/METADATA
Wrapper_Weather_Module_V2-0.0.1.dist-info/WHEEL
Wrapper_Weather_Module_V2-0.0.1.dist-info/top_level.txt
Wrapper_Weather_Module_V2-0.0.1.dist-info/RECORD
