Metadata-Version: 2.1
Name: Wrapper-Weather-Module-V2
Version: 0.0.1
Summary: Provides meaningful insights about weather forecast
Home-page: https://github.com/vkyal/DATA534_ProjectAPI
Author: Ujjwal, Varshita, Nowshabha
Author-email: upadhyay.ujjwal007@gmail.com
License: MIT
Platform: UNKNOWN
Requires-Python: >=3.9
